[
	{
		"Id": "58405b79f94c671b05350858",
		"First": "Admin",
		"Last": "Admin",
		"Email": "admin",
		"PasswordId": "57cf2b81f36d2866ee37c0c5",
		"DefaultAccountId": "58405718f94c671b05350857",
		"CreateDate":"2016-08-26T10:49:04.630536446-04:00",
		"UpdateDate":"2016-08-26T10:49:04.630536446-04:00",
		"LastLoginDate": "2016-08-26T10:49:04.630536446-04:00",
		"LastLoginIP": "",
		"Language": "en",
		"TimeZone": "US/Eastern",
		"DateFormat": "mm/dd/yyyy",
		"LastUpdateId":"57d9b383dcba0f51172f1f57",
		"EnforcePasswordChange": true,
		"BootstrapMeta": {
		}
	},
	{
		"Id": "57d9b383dcba0f51172f1f57",
		"First": "System",
		"Last": "System",
		"Email": "anonymous@system.com",
		"PasswordId": "",
		"DefaultAccountId": "",
		"CreateDate":"2016-08-26T10:49:04.630536446-04:00",
		"UpdateDate":"2016-08-26T10:49:04.630536446-04:00",
		"LastLoginDate": "2016-08-26T10:49:04.630536446-04:00",
		"LastLoginIP": "",
		"LastUpdateId":"57d9b383dcba0f51172f1f57"
	},
	{
		"Id": "5835eb61e9f1283d495114c1",
		"First": "Cron",
		"Last": "Job",
		"Email": "cronjob@system.com",
		"PasswordId": "",
		"DefaultAccountId": "",
		"CreateDate":"2016-08-26T10:49:04.630536446-04:00",
		"UpdateDate":"2016-08-26T10:49:04.630536446-04:00",
		"LastLoginDate": "2016-08-26T10:49:04.630536446-04:00",
		"LastLoginIP": "",
		"LastUpdateId":"57d9b383dcba0f51172f1f57"
	}
]
